azureml/__init__.py
azureml/train/__init__.py
azureml/train/automl/ThirdPartyNotice.txt
azureml/train/automl/__init__.py
azureml/train/automl/_amlloguploader.py
azureml/train/automl/_automl_datamodel_utilities.py
azureml/train/automl/_automl_feature_config_manager.py
azureml/train/automl/_azure_experiment_observer.py
azureml/train/automl/_azure_experiment_state.py
azureml/train/automl/_azureautomlsettings.py
azureml/train/automl/_constants_azureml.py
azureml/train/automl/_environment_utilities.py
azureml/train/automl/_execute_with_retry.py
azureml/train/automl/_inference.py
azureml/train/automl/_local_managed_startup_script.py
azureml/train/automl/_local_managed_utils.py
azureml/train/automl/_logging.py
azureml/train/automl/_model_download_utilities.py
azureml/train/automl/_remote_console_interface.py
azureml/train/automl/_remote_script.py
azureml/train/automl/_test_run_wrapper.py
azureml/train/automl/_version.py
azureml/train/automl/automl_adb_run.py
azureml/train/automl/automlconfig.py
azureml/train/automl/automlimageconfig.py
azureml/train/automl/constants.py
azureml/train/automl/exceptions.py
azureml/train/automl/model_proxy.py
azureml/train/automl/run.py
azureml/train/automl/utilities.py
azureml/train/automl/_experiment_drivers/__init__.py
azureml/train/automl/_experiment_drivers/driver_utilities.py
azureml/train/automl/_experiment_drivers/experiment_driver.py
azureml/train/automl/_experiment_drivers/local_managed_experiment_launcher.py
azureml/train/automl/_experiment_drivers/remote_experiment_launcher.py
azureml/train/automl/_hts/__init__.py
azureml/train/automl/_hts/hts_client_utilities.py
azureml/train/automl/_hts/hts_json_serializer.py
azureml/train/automl/_hts/status_record.py
azureml/train/automl/automl_model_explain/__init__.py
azureml/train/automl/client/__init__.py
azureml_train_automl_client-1.61.0.post1.dist-info/licenses/LICENSE.txt
azureml_train_automl_client-1.61.0.post1.dist-info/METADATA
azureml_train_automl_client-1.61.0.post1.dist-info/WHEEL
azureml_train_automl_client-1.61.0.post1.dist-info/entry_points.txt
azureml_train_automl_client-1.61.0.post1.dist-info/top_level.txt
azureml_train_automl_client-1.61.0.post1.dist-info/RECORD
