Metadata-Version: 2.4
Name: azureml-train-automl-client
Version: 1.61.0.post1
Summary: Used for automatically finding the best machine learning model and its parameters.
Home-page: https://docs.microsoft.com/python/api/overview/azure/ml/?view=azure-ml-py
Author: Microsoft Corp
License: https://aka.ms/azureml-sdk-license
Classifier: Development Status :: 5 - Production/Stable
Classifier: Intended Audience :: Developers
Classifier: Intended Audience :: Science/Research
Classifier: License :: Other/Proprietary License
Classifier: Programming Language :: Python :: 3.8
Classifier: Programming Language :: Python :: 3.9
Classifier: Programming Language :: Python :: 3.10
Classifier: Programming Language :: Python :: 3.11
Classifier: Topic :: Scientific/Engineering :: Artificial Intelligence
Classifier: Operating System :: Microsoft :: Windows
Classifier: Operating System :: MacOS
Classifier: Operating System :: POSIX :: Linux
Requires-Python: >=3.8,<3.12
License-File: LICENSE.txt
Requires-Dist: azureml-automl-core~=1.61.0
Requires-Dist: azureml-core~=1.61.0
Requires-Dist: azureml-dataset-runtime~=1.61.0
Requires-Dist: azureml-telemetry~=1.61.0
Requires-Dist: azureml-train-core~=1.61.0
Dynamic: author
Dynamic: classifier
Dynamic: description
Dynamic: description-content-type
Dynamic: home-page
Dynamic: license
Dynamic: license-file
Dynamic: requires-dist
Dynamic: requires-python
Dynamic: summary
